MANIFEST.in
README.md
setup.py
src/masonite_swagger_ui.egg-info/PKG-INFO
src/masonite_swagger_ui.egg-info/SOURCES.txt
src/masonite_swagger_ui.egg-info/dependency_links.txt
src/masonite_swagger_ui.egg-info/requires.txt
src/masonite_swagger_ui.egg-info/top_level.txt
src/swagger_ui/.gitignore
src/swagger_ui/__init__.py
src/swagger_ui/commands/InstallCommand.py
src/swagger_ui/commands/__init__.py
src/swagger_ui/configs/__init__.py
src/swagger_ui/configs/storage.py
src/swagger_ui/controllers/SwaggerUIController.py
src/swagger_ui/controllers/__init__.py
src/swagger_ui/providers/SwaggerUIProvider.py
src/swagger_ui/providers/__init__.py
src/swagger_ui/resources/__init__.py
src/swagger_ui/resources/templates/__init__.py
src/swagger_ui/resources/templates/oauth2-redirect.html
src/swagger_ui/resources/templates/swagger-ui.html
src/swagger_ui/routes/__init__.py
src/swagger_ui/routes/web.py
src/swagger_ui/static/__init__.py
src/swagger_ui/static/css/swagger-ui.css
src/swagger_ui/static/img/favicon-16x16.png
src/swagger_ui/static/img/favicon-32x32.png
src/swagger_ui/static/js/swagger-ui-bundle.js
src/swagger_ui/static/js/swagger-ui-standalone-preset.js
src/swagger_ui/static/js/swagger-ui.js
src/swagger_ui/static/schemas/petshop.json