Metadata-Version: 2.1
Name: masonite-swagger-ui
Version: 0.0.2
Summary: Swagger-UI package for Masonite
Home-page: https://github.com/alexpdr/masonite-swagger-ui
Author: Alex Pedersen
Author-email: me@alexpdr.dev
License: MIT
Keywords: masonie api openapi swagger swagger-ui
Platform: UNKNOWN
Classifier: Development Status :: 3 - Alpha
Classifier: Intended Audience :: Developers
Classifier: Topic :: Software Development :: Build Tools
Classifier: Environment :: Web Environment
Classifier: License :: OSI Approved :: MIT License
Classifier: Operating System :: OS Independent
Classifier: Programming Language :: Python :: 3.6
Classifier: Programming Language :: Python :: 3.7
Classifier: Topic :: Internet :: WWW/HTTP
Classifier: Topic :: Internet :: WWW/HTTP :: Dynamic Content
Classifier: Topic :: Internet :: WWW/HTTP :: WSGI
Classifier: Topic :: Software Development :: Libraries :: Application Frameworks
Classifier: Topic :: Software Development :: Libraries :: Python Modules
Provides-Extra: test
